[
  {
    "cardIDs": [
      "AA0022"
    ],
    "name": "Forced Kratos Reaction",
    "renderType": "Technology",
    "cardType": "Argo Ability",
    "game": "Odyssey",
    "cycle": "Cycle I",
    "cardSize": "Standard",
    "faq": "",
    "errata": "",
    "techType": "Combat",
    "techSubType": "Argo Ability",
    "locked": "FALSE",
    "flavorProject": "If the antikratos equations are subduing the Titans, maybe we can find a way to reverse the process and stimulate a kratos reaction",
    "requirements": [
      "Siren Armor"
    ],
    "leadsTo": [
      "Hekaton Sighting"
    ],
    "flavorTech": "Is it pain or elation?",
    "abilities": [
      {
        "effects": [
          {
            "abilityText": [
              {
                "type": "plainText",
                "value": "Choose a Titan"
              }
            ]
          },
          {
            "abilityText": [
              {
                "type": "plainText",
                "value": "That Titan may gain +1"
              },
              {
                "type": "icon",
                "value": "Rage"
              }
            ]
          }
        ]
      }
    ],
    "charges": "2",
    "trireme": "FALSE"
  },
  {
    "cardIDs": [
      "AA0023"
    ],
    "name": "Teleresuscitation",
    "renderType": "Technology",
    "cardType": "Argo Ability",
    "game": "Odyssey",
    "cycle": "Cycle I",
    "cardSize": "Standard",
    "faq": "",
    "errata": "",
    "techType": "Combat",
    "techSubType": "Argo Ability",
    "locked": "FALSE",
    "flavorProject": "The philosophers of the Last Academy are sure they found a way to stimulate an almost preternatural survival instinct",
    "requirements": [
      "Labyrinthauros Sighting"
    ],
    "leadsTo": [
      "Labyrinthauros Autopsy",
      "Specialized Trireme Weapons"
    ],
    "flavorTech": "A Titan springs back to their feet as if Hades himself compelled them",
    "abilities": [
      {
        "effects": [
          {
            "abilityText": [
              {
                "type": "plainText",
                "value": "Choose a knocked down Titan"
              }
            ]
          },
          {
            "abilityText": [
              {
                "type": "plainText",
                "value": "That Titan stands up"
              }
            ]
          }
        ]
      }
    ],
    "charges": "2",
    "trireme": "FALSE"
  },
  {
    "cardIDs": [
      "AA0024"
    ],
    "name": "Fate Sink",
    "renderType": "Technology",
    "cardType": "Argo Ability",
    "game": "Odyssey",
    "cycle": "Cycle I",
    "cardSize": "Standard",
    "faq": "",
    "errata": "",
    "techType": "Combat",
    "techSubType": "Argo Ability",
    "locked": "FALSE",
    "flavorProject": "By exerting force on the Triskelion Junction, we are able to ever so slightly alter the course of Fate itself",
    "requirements": [
      "Trireme Reach Weapons"
    ],
    "leadsTo": [
      "Hekaton Autopsy"
    ],
    "flavorTech": "Whose life have we inrrevocably changed?",
    "abilities": [
      {
        "effects": [
          {
            "abilityText": [
              {
                "type": "plainText",
                "value": "Choose a Titan"
              }
            ]
          },
          {
            "abilityText": [
              {
                "type": "plainText",
                "value": "That Titan may lose -1"
              },
              {
                "type": "icon",
                "value": "Fate"
              }
            ]
          }
        ]
      }
    ],
    "charges": "2",
    "trireme": "FALSE"
  },
  {
    "cardIDs": [
      "AA0025"
    ],
    "name": "Arrow Barrage",
    "renderType": "Technology",
    "cardType": "Argo Ability",
    "game": "Odyssey",
    "cycle": "Cycle I",
    "cardSize": "Standard",
    "faq": "",
    "errata": "",
    "techType": "Combat",
    "techSubType": "Argo Ability",
    "locked": "FALSE",
    "flavorProject": "Reinforced spear and arrow tips, as well as synchronocity training, allows ship-stationed warriors to slightly weaken the AT field of a Primordial",
    "requirements": [
      "Trireme Ranged Weapons"
    ],
    "leadsTo": [
      "Crisis Protocol",
      "Basic Support Equipment"
    ],
    "flavorTech": "Ready volley!",
    "abilities": [
      {
        "effects": [
          {
            "abilityText": [
              {
                "type": "plainText",
                "value": "Place 1 Break token or 2 Opening tokens in the Kratos Pool"
              }
            ]
          }
        ]
      }
    ],
    "charges": "3",
    "trireme": "FALSE"
  },
  {
    "cardIDs": [
      "AA0026"
    ],
    "name": "Crisis Protocol",
    "renderType": "Technology",
    "cardType": "Argo Ability",
    "game": "Odyssey",
    "cycle": "Cycle I",
    "cardSize": "Standard",
    "faq": "",
    "errata": "",
    "techType": "Combat",
    "techSubType": "Argo Ability",
    "locked": "FALSE",
    "flavorProject": "The fallen priests have uncovered a surprising Gaia connection. Through the Triskelion Junction, we may be able to stimulate some form of spontaneous healing",
    "requirements": [
      "Arrow Barrage"
    ],
    "leadsTo": [
      "Labyrinthauros Sighting"
    ],
    "flavorTech": "A new philsophical protocol allows us to tap into the lingering lifeforce of Gaia and re-direct it to or from a Titan",
    "abilities": [
      {
        "effects": [
          {
            "abilityText": [
              {
                "type": "plainText",
                "value": "Choose a Titan"
              }
            ]
          },
          {
            "abilityText": [
              {
                "type": "plainText",
                "value": "That Titan may gain or lose 2"
              },
              {
                "type": "icon",
                "value": "Danger"
              }
            ]
          }
        ]
      }
    ],
    "charges": "2",
    "trireme": "FALSE"
  },
  {
    "cardIDs": [
      "AA0027"
    ],
    "name": "Pursuer Protocol",
    "renderType": "Technology",
    "cardType": "Argo Ability",
    "game": "Odyssey",
    "cycle": "Cycle I",
    "cardSize": "Standard",
    "faq": "",
    "errata": "",
    "techType": "Combat",
    "techSubType": "Argo Ability",
    "locked": "FALSE",
    "flavorProject": "The academicians studied the Pursuer's reflex pattern and are certain they can duplicate it in the Triskelion Junction",
    "requirements": [
      "Pursuer Sighting"
    ],
    "leadsTo": [
      "Labyrinthauros Autopsy",
      "Hekaton Live Study"
    ],
    "flavorTech": "Analysis of the Hermesian Pursuer's reflexes and the 'shadow' it casts on the Triskelion Junction enables us to momentarily boost a Titan's reaction time",
    "abilities": [
      {
        "effects": [
          {
            "abilityText": [
              {
                "type": "timing",
                "value": "Reaction"
              },
              {
                "type": "plainText",
                "value": "Choose a Titan"
              }
            ]
          },
          {
            "abilityText": [
              {
                "type": "plainText",
                "value": "That Titan may move 1 space"
              }
            ]
          }
        ]
      }
    ],
    "charges": "2",
    "trireme": "FALSE"
  },
  {
    "cardIDs": [
      "BA1008"
    ],
    "name": "Trireme Ballista Fire",
    "renderType": "Technology",
    "cardType": "Argo Ability",
    "game": "Odyssey",
    "cycle": "Cycle II",
    "cardSize": "Standard",
    "faq": "",
    "errata": "",
    "techType": "Combat",
    "techSubType": "Argo Ability",
    "locked": "FALSE",
    "flavorProject": "Mere arrows and javelins are not enough to pierce the thick armor of the Spartan Primordials. We need concentrated ballista fire",
    "requirements": [
      "Temenos Armor"
    ],
    "leadsTo": [
      "Cyclonus Sighting",
      "Temenos Advanced Gear",
      "Reflex Priming"
    ],
    "flavorTech": "A well timed bolt can turn the tide of battle",
    "abilities": [
      {
        "effects": [
          {
            "abilityText": [
              {
                "type": "plainText",
                "value": "Choose a Titan performing a Power Roll"
              }
            ]
          },
          {
            "abilityText": [
              {
                "type": "plainText",
                "value": "That Titan gains"
              },
              {
                "type": "keyword",
                "value": "Power Re-roll 1"
              }
            ]
          }
        ]
      }
    ],
    "charges": "3",
    "trireme": "FALSE"
  },
  {
    "cardIDs": [
      "BA1009"
    ],
    "name": "Triskelion Power Boost",
    "renderType": "Technology",
    "cardType": "Argo Ability",
    "game": "Odyssey",
    "cycle": "Cycle II",
    "cardSize": "Standard",
    "faq": "",
    "errata": "",
    "techType": "Combat",
    "techSubType": "Argo Ability",
    "locked": "FALSE",
    "flavorProject": "There is some latent power in the Balaneion itself, power we can temporarily transfer through the junction",
    "requirements": [
      "Temenos Weapons"
    ],
    "leadsTo": [
      "Temenos Advanced Gear",
      "Chimera Metastasios Sighting",
      "Forced Kratos Cooldown"
    ],
    "flavorTech": "Is this Us exerting our strength, or something else entirely?",
    "abilities": [
      {
        "effects": [
          {
            "abilityText": [
              {
                "type": "plainText",
                "value": "Choose an attacking Titan"
              }
            ]
          },
          {
            "abilityText": [
              {
                "type": "plainText",
                "value": "That Titan gains"
              },
              {
                "type": "keyword",
                "value": "Pushback 2"
              }
            ]
          }
        ]
      }
    ],
    "charges": "2",
    "trireme": "FALSE"
  },
  {
    "cardIDs": [
      "BA1010"
    ],
    "name": "Forced Kratos Cooldown",
    "renderType": "Technology",
    "cardType": "Argo Ability",
    "game": "Odyssey",
    "cycle": "Cycle II",
    "cardSize": "Standard",
    "faq": "",
    "errata": "",
    "techType": "Combat",
    "techSubType": "Argo Ability",
    "locked": "FALSE",
    "flavorProject": "We can flood the Junction with soothing thoughts, temporarily subduing even the most violent tendencies",
    "requirements": [
      "Triskelion Power Boost"
    ],
    "leadsTo": [
      "Cyclonus Sighting"
    ],
    "flavorTech": "Can you hear me now?",
    "abilities": [
      {
        "effects": [
          {
            "abilityText": [
              {
                "type": "plainText",
                "value": "Choose a Titan that is about to gain involuntary"
              },
              {
                "type": "icon",
                "value": "Rage"
              },
              {
                "type": "plainText",
                "value": "to ignore that gain"
              }
            ]
          }
        ]
      },
      {
        "effects": [
          {
            "abilityText": [
              {
                "type": "plainText",
                "value": "Choose a Titan"
              }
            ]
          },
          {
            "abilityText": [
              {
                "type": "plainText",
                "value": "That Titan loses -1"
              },
              {
                "type": "icon",
                "value": "Rage"
              }
            ]
          }
        ]
      }
    ],
    "charges": "2",
    "trireme": "FALSE"
  },
  {
    "cardIDs": [
      "BA1011"
    ],
    "name": "Reflex Priming",
    "renderType": "Technology",
    "cardType": "Argo Ability",
    "game": "Odyssey",
    "cycle": "Cycle II",
    "cardSize": "Standard",
    "faq": "",
    "errata": "",
    "techType": "Combat",
    "techSubType": "Argo Ability",
    "locked": "FALSE",
    "flavorProject": "By slightly increasing the autonomous range of the Antikratos Protocols, we allow the Titan to take care of the lesser, more instinctive tasks, making the Junction more efficient",
    "requirements": [
      "Trireme Ballista Fire"
    ],
    "leadsTo": [
      "Chimera Metastasios Sighting"
    ],
    "flavorTech": "Extended use of Reflex Priming leads some Titans to develop motor tics",
    "abilities": [
      {
        "effects": [
          {
            "abilityText": [
              {
                "type": "plainText",
                "value": "Unexhaust 2"
              },
              {
                "type": "icon",
                "value": "Gear"
              },
              {
                "type": "plainText",
                "value": "cards among up to 2 Titans"
              }
            ]
          }
        ]
      }
    ],
    "charges": "2",
    "trireme": "FALSE"
  },
  {
    "cardIDs": [
      "BA1012"
    ],
    "name": "13th Muse Grand Cannon",
    "renderType": "Technology",
    "cardType": "Argo Ability",
    "game": "Odyssey",
    "cycle": "Cycle II",
    "cardSize": "Tarot",
    "foundIn": "Secret Deck 06",
    "faq": "",
    "errata": "",
    "techType": "Combat",
    "techSubType": "Argo Ability",
    "locked": "FALSE",
    "flavorProject": "We once found a cannon with no name and hoped we never had to use it. Today we hope it still works",
    "requirements": [
      "Temenos Advanced Gear"
    ],
    "leadsTo": [
      "Hephaestean Oxybeles",
      "Experimental Gear"
    ],
    "flavorTech": "",
    "abilities": [
      {
        "effects": [
          {
            "abilityText": [
              {
                "type": "timing",
                "value": "Start of Titan Round"
              },
              {
                "type": "plainText",
                "value": "You may choose an effect from the Payload card and roll a d10"
              }
            ]
          },
          {
            "abilityText": [
              {
                "type": "plainText",
                "value": "On a 6+, the Cannon is primed"
              }
            ]
          },
          {
            "abilityText": [
              {
                "type": "plainText",
                "value": "It remains primed until you fire, decide to prime a different effect, or the Battle ends"
              }
            ]
          }
        ]
      },
      {
        "name": "Godkiller Shot",
        "effects": [
          {
            "abilityText": [
              {
                "type": "plainText",
                "value": "When the Cannon is primed, discard 1"
              },
              {
                "type": "icon",
                "value": "Energy"
              },
              {
                "type": "plainText",
                "value": "and lose the indicated resource to fire"
              }
            ]
          }
        ]
      },
      {
        "name": "Emergency Priming",
        "effects": [
          {
            "abilityText": [
              {
                "type": "plainText",
                "value": "As a"
              },
              {
                "type": "icon",
                "value": "Reaction"
              },
              {
                "type": "plainText",
                "value": "or after drawing a BP card you may discard 1"
              },
              {
                "type": "icon",
                "value": "Energy"
              },
              {
                "type": "plainText",
                "value": "to perform an emergency priming"
              }
            ]
          },
          {
            "abilityText": [
              {
                "type": "plainText",
                "value": "Immediately choose an effect from the Payload card and roll for priming as normal"
              }
            ]
          }
        ]
      }
    ],
    "charges": "2",
    "trireme": "FALSE"
  },
  {
    "cardIDs": [
      "BA1013"
    ],
    "name": "Transport Trireme",
    "renderType": "Technology",
    "cardType": "Argo Ability",
    "game": "Odyssey",
    "cycle": "Cycle II",
    "cardSize": "Standard",
    "faq": "",
    "errata": "",
    "techType": "Combat",
    "techSubType": "Argo Ability",
    "locked": "FALSE",
    "flavorProject": "We know enough of the Great River Works canal network to use it to our advantage",
    "requirements": [
      "Cyclonus Sighting"
    ],
    "leadsTo": [
      "Experimental Gear",
      "Hephaestean Oxybeles"
    ],
    "flavorTech": "",
    "abilities": [
      {
        "name": "Rearm",
        "effects": [
          {
            "abilityText": [
              {
                "type": "plainText",
                "value": "A Titan on, adjacent to, or moving through a space with the Trireme token may flip the Trireme token to the spent side to equip any 1 Support or Weapon"
              },
              {
                "type": "icon",
                "value": "Gear"
              },
              {
                "type": "plainText",
                "value": "card from the Armory"
              }
            ]
          },
          {
            "abilityText": [
              {
                "type": "plainText",
                "value": "A spent Transport Trireme can still be moved as normal but loses the Rearm ability"
              }
            ]
          }
        ]
      }
    ],
    "charges": "",
    "trireme": "TRUE"
  },
  {
    "cardIDs": [
      "BA1014"
    ],
    "name": "Ambrosia Containment",
    "renderType": "Technology",
    "cardType": "Argo Ability",
    "game": "Odyssey",
    "cycle": "Cycle II",
    "cardSize": "Standard",
    "faq": "",
    "errata": "",
    "techType": "Combat",
    "techSubType": "Argo Ability",
    "locked": "FALSE",
    "flavorProject": "Even the Titans aren't immune to the corrupting effects of ambrosia. We need to support them however we can",
    "requirements": [
      "Chimera Metastasios Sighting"
    ],
    "leadsTo": [
      "Relief Gear"
    ],
    "flavorTech": "Specialized cleanup crews risk life and limb to minimize ambrosia exposure",
    "abilities": [
      {
        "effects": [
          {
            "abilityText": [
              {
                "type": "plainText",
                "value": "Choose a Titan that is about to gain Ambrosia tokens, lower this gain to 1"
              }
            ]
          }
        ]
      }
    ],
    "charges": "2",
    "trireme": "FALSE"
  },
  {
    "cardIDs": [
      "BA1015"
    ],
    "name": "Hephaestean Oxybeles",
    "renderType": "Technology",
    "cardType": "Argo Ability",
    "game": "Odyssey",
    "cycle": "Cycle II",
    "cardSize": "Standard",
    "faq": "",
    "errata": "",
    "techType": "Combat",
    "techSubType": "Argo Ability",
    "locked": "FALSE",
    "flavorProject": "Though everyone talks about the 13th Muse, this oxybeles design can revolutionize the way we prepare for battle",
    "requirements": [
      "13th Muse Grand Cannon",
      "Transport Trireme"
    ],
    "leadsTo": [
      "\u2014"
    ],
    "flavorTech": "",
    "abilities": [
      {
        "effects": [
          {
            "abilityText": [
              {
                "type": "plainText",
                "value": "Choose a Weapon from the Armory"
              }
            ]
          },
          {
            "abilityText": [
              {
                "type": "plainText",
                "value": "Then choose a Battle Board space you want to deploy the Weapon to and roll a d10:"
              },
              {
                "type": "newline"
              },
              {
                "type": "plainText",
                "value": "1-5: It lands 3 spaces away from the chosen space in a random direction"
              }
            ]
          },
          {
            "abilityText": [
              {
                "type": "newline"
              },
              {
                "type": "plainText",
                "value": "6-10: It lands on the chosen space"
              }
            ]
          },
          {
            "abilityText": [
              {
                "type": "plainText",
                "value": "Mark this space with a generic token"
              }
            ]
          },
          {
            "abilityText": [
              {
                "type": "newline"
              },
              {
                "type": "plainText",
                "value": "A Titan on, adjacent to, or moving through the space with the token may discard it to equip the Weapon"
              }
            ]
          },
          {
            "abilityText": [
              {
                "type": "plainText",
                "value": "If the Weapon lands on a space occupied by the Primordial, it remains stuck in its body"
              }
            ]
          },
          {
            "abilityText": [
              {
                "type": "plainText",
                "value": "Place a generic token on the Primordial Sheet and place 2 Break tokens and 1 Opening token in the Kratos Pool"
              }
            ]
          },
          {
            "abilityText": [
              {
                "type": "plainText",
                "value": "A Titan adjacent to the Primordial or on the Primordial VP may discard the generic token to equip the Weapon"
              }
            ]
          }
        ]
      }
    ],
    "charges": "2",
    "trireme": "FALSE"
  },
  {
    "cardIDs": [
      "BA1016"
    ],
    "name": "Hyperadrenaline Infusion",
    "renderType": "Technology",
    "cardType": "Argo Ability",
    "game": "Odyssey",
    "cycle": "Cycle II",
    "cardSize": "Standard",
    "faq": "",
    "errata": "",
    "techType": "Combat",
    "techSubType": "Argo Ability",
    "locked": "FALSE",
    "flavorProject": "By stimulating the Titan's adrenal glands through the Junction, we can manufacture an incredible reflex reaction",
    "requirements": [
      "Temenos Support Equipment"
    ],
    "leadsTo": [
      "War Support Equipment"
    ],
    "flavorTech": "Is there a limit to the Titan's power?",
    "abilities": [
      {
        "effects": [
          {
            "abilityText": [
              {
                "type": "plainText",
                "value": "Choose a Titan that is about to perform a voluntary movement"
              }
            ]
          },
          {
            "abilityText": [
              {
                "type": "plainText",
                "value": "That Titan may move 4 more spaces during this movement"
              }
            ]
          }
        ]
      }
    ],
    "charges": "1",
    "trireme": "FALSE"
  },
  {
    "cardIDs": [
      "BA1017"
    ],
    "name": "Pursuer Order",
    "renderType": "Technology",
    "cardType": "Argo Ability",
    "game": "Odyssey",
    "cycle": "Cycle II",
    "cardSize": "Standard",
    "faq": "",
    "errata": "",
    "techType": "Combat",
    "techSubType": "Argo Ability",
    "locked": "FALSE",
    "flavorProject": "The study of the recovered cryptex has led to a breakthrough in Junction Theory",
    "requirements": [
      "Bronze Lair"
    ],
    "leadsTo": [
      "\u2014"
    ],
    "flavorTech": "The wings of oppression overturned now lift you up",
    "abilities": [
      {
        "effects": [
          {
            "abilityText": [
              {
                "type": "timing",
                "value": "Reaction"
              },
              {
                "type": "plainText",
                "value": "Choose a Titan"
              }
            ]
          },
          {
            "abilityText": [
              {
                "type": "plainText",
                "value": "That Titan may move up to 2 spaces"
              }
            ]
          }
        ]
      }
    ],
    "charges": "2",
    "trireme": "FALSE"
  },
  {
    "cardIDs": [
      "BA1018"
    ],
    "name": "Rendezvous Trireme",
    "renderType": "Technology",
    "cardType": "Argo Ability",
    "game": "Odyssey",
    "cycle": "Cycle II",
    "cardSize": "Standard",
    "faq": "",
    "errata": "",
    "techType": "Combat",
    "techSubType": "Argo Ability",
    "locked": "FALSE",
    "flavorProject": "You still remember that fateful rendezvous with the Symmachy. O strange bedfellows",
    "requirements": [
      "Symmachy Alliance"
    ],
    "leadsTo": [
      "\u2014"
    ],
    "flavorTech": "",
    "abilities": [
      {
        "name": "Housewarming Gift",
        "effects": [
          {
            "abilityText": [
              {
                "type": "plainText",
                "value": "If you push the Primordial on to a space with the Trireme token, discard the token and place 1 negative"
              },
              {
                "type": "icon",
                "value": "AT"
              },
              {
                "type": "plainText",
                "value": "token in the Kratos Pool"
              }
            ]
          },
          {
            "abilityText": [
              {
                "type": "plainText",
                "value": "If the Primordial moves through a space with the Trireme token, discard the token, then roll a d10"
              }
            ]
          },
          {
            "abilityText": [
              {
                "type": "plainText",
                "value": "On a 6+, place 1 negative"
              },
              {
                "type": "icon",
                "value": "AT"
              },
              {
                "type": "plainText",
                "value": "token in the Kratos Pool"
              }
            ]
          }
        ]
      }
    ],
    "charges": "",
    "trireme": "TRUE"
  },
  {
    "cardIDs": [
      "CA1597"
    ],
    "name": "Fate Converter",
    "renderType": "Technology",
    "cardType": "Argo Ability",
    "game": "Odyssey",
    "cycle": "Cycle III",
    "cardSize": "Standard",
    "faq": "",
    "errata": "",
    "techType": "Combat",
    "techSubType": "Argo Ability",
    "locked": "FALSE",
    "flavorProject": "A Moirai verdict can be resisted, you have seen proof of that",
    "requirements": [
      "Nietzschean Reach Weapons",
      "Nietzschean Armor"
    ],
    "leadsTo": [
      "Hypertime Oracle Sighting",
      "Icarian Harpy Sighting"
    ],
    "flavorTech": "Weaponized free will",
    "abilities": [
      {
        "effects": [
          {
            "abilityText": [
              {
                "type": "plainText",
                "value": "Choose a Titan"
              }
            ]
          },
          {
            "abilityText": [
              {
                "type": "plainText",
                "value": "That Titan loses -2"
              },
              {
                "type": "icon",
                "value": "Fate"
              },
              {
                "type": "plainText",
                "value": "and gains +1"
              },
              {
                "type": "icon",
                "value": "Danger"
              }
            ]
          }
        ]
      }
    ],
    "charges": "3",
    "trireme": "FALSE"
  },
  {
    "cardIDs": [
      "CA1598"
    ],
    "name": "Reverse Timeflow",
    "renderType": "Technology",
    "cardType": "Argo Ability",
    "game": "Odyssey",
    "cycle": "Cycle III",
    "cardSize": "Standard",
    "faq": "",
    "errata": "",
    "techType": "Combat",
    "techSubType": "Argo Ability",
    "locked": "FALSE",
    "flavorProject": "Reverse-engineered reversed time",
    "requirements": [
      "Nietzschean Reach Weapons",
      "Nietzschean Armor"
    ],
    "leadsTo": [
      "Delphian Siren Armor",
      "Delphian Siren Weapons",
      "Hypertime Oracle Sighting"
    ],
    "flavorTech": "Fast-tracked to victory",
    "abilities": [
      {
        "effects": [
          {
            "abilityText": [
              {
                "type": "plainText",
                "value": "Choose a Titan"
              }
            ]
          },
          {
            "abilityText": [
              {
                "type": "plainText",
                "value": "That Titan arrives from Time-clocked"
              }
            ]
          }
        ]
      }
    ],
    "charges": "2",
    "trireme": "FALSE"
  },
  {
    "cardIDs": [
      "CA1599"
    ],
    "name": "Possibility Matrix",
    "renderType": "Technology",
    "cardType": "Argo Ability",
    "game": "Odyssey",
    "cycle": "Cycle III",
    "cardSize": "Standard",
    "faq": "",
    "errata": "",
    "techType": "Combat",
    "techSubType": "Argo Ability",
    "locked": "FALSE",
    "flavorProject": "The Oracle prunes possible outcomes, we need to multiply them",
    "requirements": [
      "Temporal Support Equipment",
      "Nietzschean Weapons"
    ],
    "leadsTo": [
      "Delphian Siren Armor",
      "Delphian Siren Weapons",
      "Icarian Harpy Sighting"
    ],
    "flavorTech": "From the infinite pool of outcomes, survival requires just one",
    "abilities": [
      {
        "effects": [
          {
            "abilityText": [
              {
                "type": "plainText",
                "value": "Place the top card of any Trauma deck on the bottom of that deck"
              }
            ]
          },
          {
            "abilityText": [
              {
                "type": "plainText",
                "value": "You may use this ability as a free action or as a"
              },
              {
                "type": "icon",
                "value": "Reaction"
              }
            ]
          }
        ]
      }
    ],
    "charges": "2",
    "trireme": "FALSE"
  },
  {
    "cardIDs": [
      "CA1600"
    ],
    "name": "Telehealing",
    "renderType": "Technology",
    "cardType": "Argo Ability",
    "game": "Odyssey",
    "cycle": "Cycle III",
    "cardSize": "Standard",
    "faq": "",
    "errata": "",
    "techType": "Combat",
    "techSubType": "Argo Ability",
    "locked": "FALSE",
    "flavorProject": "We know how to stimulate healing through the Junction, though we don't know how it works",
    "requirements": [
      "Temporal Support Equipment",
      "Nietzschean Weapons"
    ],
    "leadsTo": [
      "Hypertime Oracle Sighting",
      "Icarian Harpy Sighting"
    ],
    "flavorTech": "I see you, my children",
    "abilities": [
      {
        "effects": [
          {
            "abilityText": [
              {
                "type": "plainText",
                "value": "Discard up 2 to Bleeding tokens from a chosen Titan"
              }
            ]
          }
        ]
      }
    ],
    "charges": "2",
    "trireme": "FALSE"
  },
  {
    "cardIDs": [
      "CA1601"
    ],
    "name": "Transient Death",
    "renderType": "Technology",
    "cardType": "Argo Ability",
    "game": "Odyssey",
    "cycle": "Cycle III",
    "cardSize": "Standard",
    "faq": "",
    "errata": "",
    "techType": "Combat",
    "techSubType": "Argo Ability",
    "locked": "TRUE",
    "flavorProject": "By bending the Delphian Loop, we can bring back a recently deceased Titan to life. For a price...",
    "requirements": [
      "Argoline Transforming Weapons"
    ],
    "leadsTo": [
      "\u2014"
    ],
    "flavorTech": "Even death may die",
    "abilities": [
      {
        "effects": [
          {
            "abilityText": [
              {
                "type": "plainText",
                "value": "Lose -1 Titan from the"
              },
              {
                "type": "italics",
                "value": "Argo"
              },
              {
                "type": "plainText",
                "value": "to choose a dead Titan"
              }
            ]
          },
          {
            "abilityText": [
              {
                "type": "plainText",
                "value": "That Titan comes back to life at their Time Anchor"
              }
            ]
          },
          {
            "abilityText": [
              {
                "type": "plainText",
                "value": "You may use this ability as a free action or as a"
              },
              {
                "type": "icon",
                "value": "Reaction"
              }
            ]
          }
        ]
      }
    ],
    "charges": "1",
    "trireme": "FALSE"
  },
  {
    "cardIDs": [
      "CA1602"
    ],
    "name": "Quantum Armory",
    "renderType": "Technology",
    "cardType": "Argo Ability",
    "game": "Odyssey",
    "cycle": "Cycle III",
    "cardSize": "Standard",
    "faq": "",
    "errata": "",
    "techType": "Combat",
    "techSubType": "Argo Ability",
    "locked": "FALSE",
    "flavorProject": "Slightly shifting the timeline allows us to re-arm the Titans in the past",
    "requirements": [
      "Icarian Harpy Sighting"
    ],
    "leadsTo": [
      "Icarian Harpy Autopsy"
    ],
    "flavorTech": "For each task, the perfect tool",
    "abilities": [
      {
        "effects": [
          {
            "abilityText": [
              {
                "type": "plainText",
                "value": "Immediately equip 1 Weapon from the Argo Armory"
              }
            ]
          },
          {
            "abilityText": [
              {
                "type": "plainText",
                "value": "You may swap it with one of your currently equipped Weapons (return it to the Argo Armory)"
              }
            ]
          },
          {
            "abilityText": [
              {
                "type": "plainText",
                "value": "You may use this ability as a free action or when you are about to perform a"
              },
              {
                "type": "bold",
                "value": "Bonus Attack"
              }
            ]
          }
        ]
      }
    ],
    "charges": "2",
    "trireme": "FALSE"
  },
  {
    "cardIDs": [
      "CA1603"
    ],
    "name": "Opportunity Freeze",
    "renderType": "Technology",
    "cardType": "Argo Ability",
    "game": "Odyssey",
    "cycle": "Cycle III",
    "cardSize": "Standard",
    "faq": "",
    "errata": "",
    "techType": "Combat",
    "techSubType": "Argo Ability",
    "locked": "FALSE",
    "flavorProject": "Slowing down time to extend your window of opportunity",
    "requirements": [
      "Hypertime Oracle Sighting"
    ],
    "leadsTo": [
      "Hypertime Oracle Autopsy"
    ],
    "flavorTech": "Everyone deserves a second chance",
    "abilities": [
      {
        "effects": [
          {
            "abilityText": [
              {
                "type": "plainText",
                "value": "When a Titan fully misses an Attack, do not clear the Kratos Pool"
              }
            ]
          }
        ]
      }
    ],
    "charges": "2",
    "trireme": "FALSE"
  },
  {
    "cardIDs": [
      "CA1604"
    ],
    "name": "Chronosphere Warning System",
    "renderType": "Technology",
    "cardType": "Argo Ability",
    "game": "Odyssey",
    "cycle": "Cycle III",
    "cardSize": "Standard",
    "faq": "",
    "errata": "",
    "techType": "Combat",
    "techSubType": "Argo Ability",
    "locked": "FALSE",
    "flavorProject": "Monitoring the flow of time grants Titans near precognitive reflexes",
    "requirements": [
      "Delphian Siren Armor",
      "Delphian Siren Weapons"
    ],
    "leadsTo": [
      "Black Ice Armor",
      "Atemporal Support Equipment"
    ],
    "flavorTech": "Forecast: Survival",
    "abilities": [
      {
        "effects": [
          {
            "abilityText": [
              {
                "type": "icon",
                "value": "Reaction"
              },
              {
                "type": "plainText",
                "value": "Choose a Titan"
              }
            ]
          },
          {
            "abilityText": [
              {
                "type": "plainText",
                "value": "That Titan may move up to 3 spaces"
              }
            ]
          }
        ]
      }
    ],
    "charges": "2",
    "trireme": "FALSE"
  },
  {
    "cardIDs": [
      "CA1605"
    ],
    "name": "Time Skip",
    "renderType": "Technology",
    "cardType": "Argo Ability",
    "game": "Odyssey",
    "cycle": "Cycle III",
    "cardSize": "Standard",
    "faq": "",
    "errata": "",
    "techType": "Combat",
    "techSubType": "Argo Ability",
    "locked": "FALSE",
    "flavorProject": "The study of the recovered cryptex has led to a breakthrough in Junction Theory",
    "requirements": [
      "Icarian Harpy Autopsy"
    ],
    "leadsTo": [
      "Icarian Harpy Live Study"
    ],
    "flavorTech": "--Dovahzul text--",
    "abilities": [
      {
        "effects": [
          {
            "abilityText": [
              {
                "type": "plainText",
                "value": "During a Titan turn, even after you have used both of your actions, choose a Titan"
              }
            ]
          },
          {
            "abilityText": [
              {
                "type": "plainText",
                "value": "That Titan may imediately perform an additional"
              },
              {
                "type": "icon",
                "value": "CombatAction"
              }
            ]
          }
        ]
      }
    ],
    "charges": "1",
    "trireme": "FALSE"
  },
  {
    "cardIDs": [
      "CA1606"
    ],
    "name": "Time Dilation",
    "renderType": "Technology",
    "cardType": "Argo Ability",
    "game": "Odyssey",
    "cycle": "Cycle III",
    "cardSize": "Standard",
    "faq": "",
    "errata": "",
    "techType": "Combat",
    "techSubType": "Argo Ability",
    "locked": "FALSE",
    "flavorProject": "Slowing time inside the Junction",
    "requirements": [
      "Hypertime Oracle Autopsy"
    ],
    "leadsTo": [
      "Hypertime Oracle Live Study"
    ],
    "flavorTech": "--Dovahzul text--",
    "abilities": [
      {
        "effects": [
          {
            "abilityText": [
              {
                "type": "plainText",
                "value": "During a Titan turn, even after you have used both of your actions, choose a Titan"
              }
            ]
          },
          {
            "abilityText": [
              {
                "type": "plainText",
                "value": "That Titan may imediately perform an additional"
              },
              {
                "type": "icon",
                "value": "MovementAction"
              }
            ]
          }
        ]
      }
    ],
    "charges": "1",
    "trireme": "FALSE"
  },
  {
    "cardIDs": [
      "DA2188"
    ],
    "name": "Irem Protocols",
    "renderType": "Technology",
    "cardType": "Argo Ability",
    "game": "Odyssey",
    "cycle": "Cycle IV",
    "cardSize": "Standard",
    "faq": "",
    "errata": "",
    "techType": "Combat",
    "techSubType": "Argo Ability",
    "locked": "FALSE",
    "flavorProject": "Our scholars have broken the wish-codes used to hide the towers in the sand",
    "requirements": [
      "Cinder Support",
      "Cinder Ranged Weapons"
    ],
    "leadsTo": [
      "Gold Transmogrifier",
      "Imperial Deprived Stockpile"
    ],
    "flavorTech": "Action exigent: Emergy retraction",
    "abilities": [
      {
        "effects": [
          {
            "abilityText": [
              {
                "type": "plainText",
                "value": "Move an empty Irem Tower Terrain tile any number of spaces in a straight line"
              }
            ]
          },
          {
            "abilityText": [
              {
                "type": "plainText",
                "value": "It cannot move through other Terrain tiles or the Primordial"
              }
            ]
          }
        ]
      }
    ],
    "charges": "3",
    "trireme": "FALSE"
  },
  {
    "cardIDs": [
      "DA2189"
    ],
    "name": "Wish Deflector",
    "renderType": "Technology",
    "cardType": "Argo Ability",
    "game": "Odyssey",
    "cycle": "Cycle IV",
    "cardSize": "Standard",
    "faq": "",
    "errata": "",
    "techType": "Combat",
    "techSubType": "Argo Ability",
    "locked": "FALSE",
    "flavorProject": "When properly calibrated, Delphian paracausal shielding can provide a brief respit from the barrage of wishes",
    "requirements": [
      "Cinder Ranged Weapons",
      "Cinder Armor"
    ],
    "leadsTo": [
      "Imperial Deprived Outfitter"
    ],
    "flavorTech": "Wishing you did not have to wish",
    "abilities": [
      {
        "effects": [
          {
            "abilityText": [
              {
                "type": "plainText",
                "value": "When a Titan becomes the Target of a Wish Attack, choose that Titan"
              }
            ]
          },
          {
            "abilityText": [
              {
                "type": "plainText",
                "value": "That Titan gains"
              },
              {
                "type": "keyword",
                "value": "Wish Armor"
              }
            ]
          }
        ]
      }
    ],
    "charges": "2",
    "trireme": "FALSE"
  },
  {
    "cardIDs": [
      "DA2190"
    ],
    "name": "Gold Transmogrifier",
    "renderType": "Technology",
    "cardType": "Argo Ability",
    "game": "Odyssey",
    "cycle": "Cycle IV",
    "cardSize": "Standard",
    "faq": "",
    "errata": "",
    "techType": "Combat",
    "techSubType": "Argo Ability",
    "locked": "FALSE",
    "flavorProject": "This alchemical process is highly unstable but remains the fastest known converter",
    "requirements": [
      "Irem Protocols"
    ],
    "leadsTo": [
      "Midascore Sighting"
    ],
    "flavorTech": "Like a million tiny wishes",
    "abilities": [
      {
        "effects": [
          {
            "abilityText": [
              {
                "type": "plainText",
                "value": "Choose a Titan and roll 2"
              },
              {
                "type": "icon",
                "value": "BlackPowerDie"
              }
            ]
          },
          {
            "abilityText": [
              {
                "type": "plainText",
                "value": "Count the number of"
              },
              {
                "type": "icon",
                "value": "Power"
              }
            ]
          },
          {
            "abilityText": [
              {
                "type": "plainText",
                "value": "Turn as many of that Titan's Midas tokens into Ambrosia tokens"
              }
            ]
          }
        ]
      }
    ],
    "charges": "2",
    "trireme": "FALSE"
  },
  {
    "cardIDs": [
      "DA2191"
    ],
    "name": "Archimedean Ballista",
    "renderType": "Technology",
    "cardType": "Argo Ability",
    "game": "Odyssey",
    "cycle": "Cycle IV",
    "cardSize": "Standard",
    "faq": "",
    "errata": "",
    "techType": "Combat",
    "techSubType": "Argo Ability",
    "locked": "FALSE",
    "flavorProject": "Next generation of weapons utilizing the devasting power of the Sun",
    "requirements": [
      "Imperial Deprived Armorer"
    ],
    "leadsTo": [
      "Demidjinn Sighting"
    ],
    "flavorTech": "Not a ballista at all",
    "abilities": [
      {
        "effects": [
          {
            "abilityText": [
              {
                "type": "plainText",
                "value": "Place 3 Opening tokens or 2 Fire tokens in the Kratos Pool"
              }
            ]
          }
        ]
      }
    ],
    "charges": "2",
    "trireme": "FALSE"
  },
  {
    "cardIDs": [
      "DA2192"
    ],
    "name": "Cloud Support Fleet",
    "renderType": "Technology",
    "cardType": "Argo Ability",
    "game": "Odyssey",
    "cycle": "Cycle IV",
    "cardSize": "Standard",
    "faq": "",
    "errata": "",
    "techType": "Combat",
    "techSubType": "Argo Ability",
    "locked": "FALSE",
    "flavorProject": "Our enemies dominate the skies. We need to wrest air superiority away from them",
    "requirements": [
      "Midascore Sighting"
    ],
    "leadsTo": [
      "Midascore Autopsy",
      "Old Irem Excavation"
    ],
    "flavorTech": "We have adapted the local \"cirrotrireme\" technology, though our cloud vessels remain inferior to the fleet of the Empire",
    "abilities": [
      {
        "effects": [
          {
            "abilityText": [
              {
                "type": "keyword",
                "value": "Elevated"
              }
            ]
          },
          {
            "abilityText": [
              {
                "type": "plainText",
                "value": "Place the Cirrotrireme token or move the Cirrotrireme token to any space on the Battle Board (even if occupied)"
              }
            ]
          }
        ]
      },
      {
        "name": "Rearm",
        "effects": [
          {
            "abilityText": [
              {
                "type": "plainText",
                "value": "A Titan on, adjacent to, or moving through a space with the Cirrotrireme token may flip the token to the spent side to equip any 1 Weapon"
              },
              {
                "type": "icon",
                "value": "Gear"
              },
              {
                "type": "plainText",
                "value": "card from the Armory"
              }
            ]
          },
          {
            "abilityText": [
              {
                "type": "plainText",
                "value": "A spent Cirrotrieme can still be moved as normal but loses the"
              },
              {
                "type": "bold",
                "value": "Rearm"
              },
              {
                "type": "plainText",
                "value": "ability"
              }
            ]
          }
        ]
      }
    ],
    "charges": "3",
    "trireme": "TRUE"
  },
  {
    "cardIDs": [
      "DA2193"
    ],
    "name": "Dahaka Phasing",
    "renderType": "Technology",
    "cardType": "Argo Ability",
    "game": "Odyssey",
    "cycle": "Cycle IV",
    "cardSize": "Standard",
    "faq": "",
    "errata": "",
    "techType": "Combat",
    "techSubType": "Argo Ability",
    "locked": "FALSE",
    "flavorProject": "Dahaka's signature in the Triskelion is like a tempestuous wind or tide. If we could surf it...",
    "requirements": [
      "Dahaka Sighting"
    ],
    "leadsTo": [
      "Insolvency Bulwark",
      "Dahaka Autopsy",
      "Midascore Autospy",
      "Demidjinn Live Study"
    ],
    "flavorTech": "Anemoi reflex",
    "abilities": [
      {
        "effects": [
          {
            "abilityText": [
              {
                "type": "icon",
                "value": "Reaction"
              },
              {
                "type": "plainText",
                "value": "Choose a Titan"
              }
            ]
          },
          {
            "abilityText": [
              {
                "type": "plainText",
                "value": "That Titan may perform"
              },
              {
                "type": "keyword",
                "value": "Hermes Move 1"
              }
            ]
          }
        ]
      }
    ],
    "charges": "2",
    "trireme": "FALSE"
  },
  {
    "cardIDs": [
      "DA2194"
    ],
    "name": "Cloud Scout Fleet",
    "renderType": "Technology",
    "cardType": "Argo Ability",
    "game": "Odyssey",
    "cycle": "Cycle IV",
    "cardSize": "Standard",
    "faq": "",
    "errata": "",
    "techType": "Combat",
    "techSubType": "Argo Ability",
    "locked": "FALSE",
    "flavorProject": "We need to develop a lighter, faster method for reconnaissance and extraction",
    "requirements": [
      "Old Irem Composite Shop"
    ],
    "leadsTo": [
      "Midascore Live Study"
    ],
    "flavorTech": "Second generation cloudships, hemiolias of the skies",
    "abilities": [
      {
        "effects": [
          {
            "abilityText": [
              {
                "type": "plainText",
                "value": "Choose a Titan that is being Wished Away"
              }
            ]
          },
          {
            "abilityText": [
              {
                "type": "plainText",
                "value": "Reduce that suffered Wish Away by up to -4"
              }
            ]
          },
          {
            "abilityText": [
              {
                "type": "plainText",
                "value": "You may place that Titan on any Irem Tower within range (not necessarily in front of the Primordial)"
              }
            ]
          }
        ]
      }
    ],
    "charges": "2",
    "trireme": "FALSE"
  },
  {
    "cardIDs": [
      "DA2195"
    ],
    "name": "Ascension Protocols",
    "renderType": "Technology",
    "cardType": "Argo Ability",
    "game": "Odyssey",
    "cycle": "Cycle IV",
    "cardSize": "Standard",
    "faq": "",
    "errata": "",
    "techType": "Combat",
    "techSubType": "Argo Ability",
    "locked": "FALSE",
    "flavorProject": "The Babelian Lunacy is an ever-changing architectural impossibility. Maybe we should treat it like a current, not a structure?",
    "requirements": [
      "Demidjinn Autospy"
    ],
    "leadsTo": [
      "Demidjinn Live Study"
    ],
    "flavorTech": "Insider shortcuts",
    "abilities": [
      {
        "effects": [
          {
            "abilityText": [
              {
                "type": "plainText",
                "value": "Choose a Titan performing an Ascent check"
              }
            ]
          },
          {
            "abilityText": [
              {
                "type": "plainText",
                "value": "Add +3 to the result"
              }
            ]
          }
        ]
      }
    ],
    "charges": "2",
    "trireme": "FALSE"
  },
  {
    "cardIDs": [
      "DA2196"
    ],
    "name": "Curse Resistor",
    "renderType": "Technology",
    "cardType": "Argo Ability",
    "game": "Odyssey",
    "cycle": "Cycle IV",
    "cardSize": "Standard",
    "faq": "",
    "errata": "",
    "techType": "Combat",
    "techSubType": "Argo Ability",
    "locked": "FALSE",
    "flavorProject": "We need to undersatnd the underlying imbalance of the curses",
    "requirements": [
      "Old Irem Dig"
    ],
    "leadsTo": [
      "Demidjinn Autopsy",
      "True Value of Life"
    ],
    "flavorTech": "By dividing the curse between several willing participants simultaneously, we weaken its effects",
    "abilities": [
      {
        "effects": [
          {
            "abilityText": [
              {
                "type": "plainText",
                "value": "Choose a Titan"
              }
            ]
          },
          {
            "abilityText": [
              {
                "type": "plainText",
                "value": "Either:"
              },
              {
                "type": "plainText",
                "value": "Flip one of that Titan's Condition cards"
              }
            ],
            "costs": [
              "Energy"
            ]
          },
          {
            "abilityText": [
              {
                "type": "plainText",
                "value": "Discard one of that Titan's Condition cards"
              }
            ],
            "costs": [
              "Energy",
              "Energy"
            ]
          }
        ]
      }
    ],
    "charges": "2",
    "trireme": "FALSE"
  },
  {
    "cardIDs": [
      "DA2223"
    ],
    "name": "Ropeseller Theorem",
    "renderType": "Technology",
    "cardType": "Argo Ability",
    "game": "Odyssey",
    "cycle": "Cycle IV",
    "cardSize": "Standard",
    "foundIn": "Secret Deck 13",
    "faq": "",
    "errata": "",
    "techType": "Combat",
    "techSubType": "Argo Ability",
    "locked": "FALSE",
    "flavorProject": "Greed stronger than survival",
    "requirements": [
      "\u2014"
    ],
    "leadsTo": [
      "\u2014"
    ],
    "flavorTech": "In the end, it defeats itself",
    "abilities": [
      {
        "effects": [
          {
            "abilityText": [
              {
                "type": "plainText",
                "value": "When the Primordial reveals an AI card or triggers a Signature that targets a specific Titan, change the Targeting to"
              },
              {
                "type": "bold",
                "value": "Target:"
              },
              {
                "type": "plainText",
                "value": "Most Midas tokens"
              }
            ]
          }
        ]
      }
    ],
    "charges": "1",
    "trireme": "FALSE"
  },
  {
    "cardIDs": [
      "EA2750"
    ],
    "name": "Calculate Statistical Certainty",
    "renderType": "Technology",
    "cardType": "Argo Ability",
    "game": "Odyssey",
    "cycle": "Cycle V",
    "cardSize": "Standard",
    "faq": "",
    "errata": "",
    "techType": "Combat",
    "techSubType": "Argo Ability",
    "locked": "FALSE",
    "flavorProject": "A wise and ancient advisor of unknown origin, brought into existence by the wonders of Mnestis. It always tells the truth, no matter how bleak it is",
    "requirements": [
      "Babelian Ranged Weapons",
      "Babelian Support"
    ],
    "leadsTo": [
      "Abyss Support",
      "Oxygen Tubes",
      "Ur-Fleece Sighting"
    ],
    "flavorTech": "Chance of survival: bleak",
    "abilities": [
      {
        "effects": [
          {
            "abilityText": [
              {
                "type": "plainText",
                "value": "Choose a Titan"
              }
            ]
          },
          {
            "abilityText": [
              {
                "type": "plainText",
                "value": "That Titan uses the Truth Machine"
              }
            ]
          }
        ]
      }
    ],
    "charges": "3",
    "trireme": "FALSE"
  },
  {
    "cardIDs": [
      "EA2751"
    ],
    "name": "Kintsukuroi Pharos",
    "renderType": "Technology",
    "cardType": "Argo Ability",
    "game": "Odyssey",
    "cycle": "Cycle V",
    "cardSize": "Standard",
    "faq": "",
    "errata": "",
    "techType": "Combat",
    "techSubType": "Argo Ability",
    "locked": "FALSE",
    "flavorProject": "This giant searchlight is an unexpected by-product of the Last Wish. This is the 13th Muse, reconstructed",
    "requirements": [
      "Babelian Armor",
      "Babelian Ranged Weapons"
    ],
    "leadsTo": [
      "Abyss Weapons",
      "Drag It Back!"
    ],
    "flavorTech": "There is value in mending broken things",
    "abilities": [
      {
        "effects": [
          {
            "abilityText": [
              {
                "type": "timing",
                "value": "Start of Battle"
              },
              {
                "type": "plainText",
                "value": "Choose one Kintsukuroi Pharos Payload and place it on this card"
              }
            ]
          },
          {
            "abilityText": [
              {
                "type": "plainText",
                "value": "Until the end of Battle, the Payload becomes the effect of this Argo Ability"
              }
            ]
          }
        ]
      }
    ],
    "charges": "1",
    "trireme": "FALSE"
  },
  {
    "cardIDs": [
      "EA2752"
    ],
    "name": "Oxygen Tubes",
    "renderType": "Technology",
    "cardType": "Argo Ability",
    "game": "Odyssey",
    "cycle": "Cycle V",
    "cardSize": "Standard",
    "faq": "",
    "errata": "",
    "techType": "Combat",
    "techSubType": "Argo Ability",
    "locked": "FALSE",
    "flavorProject": "Made from Primordial intestines, they carry life-saving air from the Argo",
    "requirements": [
      "Calculate Statistical Certainty"
    ],
    "leadsTo": [
      "Dragon of Phobos Sighting"
    ],
    "flavorTech": "Time bought",
    "abilities": [
      {
        "effects": [
          {
            "abilityText": [
              {
                "type": "plainText",
                "value": "Choose a Titan"
              }
            ]
          },
          {
            "abilityText": [
              {
                "type": "plainText",
                "value": "That Titan flips 1 Aether token"
              }
            ]
          }
        ]
      }
    ],
    "charges": "2",
    "trireme": "FALSE"
  },
  {
    "cardIDs": [
      "EA2753"
    ],
    "name": "Drag It Back!",
    "renderType": "Technology",
    "cardType": "Argo Ability",
    "game": "Odyssey",
    "cycle": "Cycle V",
    "cardSize": "Standard",
    "faq": "",
    "errata": "",
    "techType": "Combat",
    "techSubType": "Argo Ability",
    "locked": "FALSE",
    "flavorProject": "Giant harpoon guns mounted on the Argo itself",
    "requirements": [
      "Kintsukuroi Pharos"
    ],
    "leadsTo": [
      "Meduketos Sighting"
    ],
    "flavorTech": "Fire forward harpoons!",
    "abilities": [
      {
        "effects": [
          {
            "abilityText": [
              {
                "type": "plainText",
                "value": "The Titan closest to the Primordial immediately performs Pushback X or Pull X, where X is up to 3"
              }
            ]
          }
        ]
      }
    ],
    "charges": "2",
    "trireme": "FALSE"
  },
  {
    "cardIDs": [
      "EA2754"
    ],
    "name": "Underwater Support Fleet",
    "renderType": "Technology",
    "cardType": "Argo Ability",
    "game": "Odyssey",
    "cycle": "Cycle V",
    "cardSize": "Standard",
    "faq": "",
    "errata": "",
    "techType": "Combat",
    "techSubType": "Argo Ability",
    "locked": "FALSE",
    "flavorProject": "A reclaimed Atlantean deepsea ship serves as the eyes and ears of the Titans",
    "requirements": [
      "Dragon of Phobos Sighting"
    ],
    "leadsTo": [
      "Dragon of Phobos Autopsy"
    ],
    "flavorTech": "A Galeos-class subreme, like the ones you use as harpoon tips...",
    "abilities": [
      {
        "effects": [
          {
            "abilityText": [
              {
                "type": "plainText",
                "value": "Place the Subreme token on any space adjacent to the Board Edge and move it up to 5 spaces, or if the Subreme is already on the Board, move it up to 5 spaces (even if occupied)"
              }
            ]
          },
          {
            "abilityText": [
              {
                "type": "plainText",
                "value": "A spent Subreme can still be moved as normal but loses the"
              },
              {
                "type": "bold",
                "value": "Rearm"
              },
              {
                "type": "plainText",
                "value": "and"
              },
              {
                "type": "bold",
                "value": "Detect"
              },
              {
                "type": "plainText",
                "value": "abilities"
              }
            ]
          }
        ]
      },
      {
        "name": "Rearm",
        "effects": [
          {
            "abilityText": [
              {
                "type": "plainText",
                "value": "A Titan on, adjacent to, or moving through the space with the Subreme token may flip the token to the spent side to equip any 1 Weapon card from the Armory or flip an Aether token"
              }
            ]
          }
        ]
      },
      {
        "name": "Detect",
        "effects": [
          {
            "abilityText": [
              {
                "type": "plainText",
                "value": "Flip the Subreme token to the spent side to perform a Scan"
              }
            ]
          }
        ]
      }
    ],
    "charges": "4",
    "trireme": "TRUE"
  },
  {
    "cardIDs": [
      "EA2755"
    ],
    "name": "Flash Backstep",
    "renderType": "Technology",
    "cardType": "Argo Ability",
    "game": "Odyssey",
    "cycle": "Cycle V",
    "cardSize": "Standard",
    "faq": "",
    "errata": "",
    "techType": "Combat",
    "techSubType": "Argo Ability",
    "locked": "FALSE",
    "flavorProject": "You're still far from reaching the limits of cryptext tekne, though further gains will be paid by the pain of the subject",
    "requirements": [
      "Titan X Sighting"
    ],
    "leadsTo": [
      "Atlantean Weapons",
      "Dragon of Phobos Autopsy",
      "Meduketos Live Study",
      "Silvered Armor",
      "Triskelion Override",
      "Titan X Investigation"
    ],
    "flavorTech": "Is pain elation? Or are you projecting?",
    "abilities": [
      {
        "effects": [
          {
            "abilityText": [
              {
                "type": "plainText",
                "value": "Choose a Titan when an adjacent Primordial performs"
              },
              {
                "type": "keyword",
                "value": "Flash Step"
              },
              {
                "type": "plainText",
                "value": ","
              },
              {
                "type": "keyword",
                "value": "Vanish"
              },
              {
                "type": "plainText",
                "value": ", or"
              },
              {
                "type": "keyword",
                "value": "Flicker"
              }
            ]
          },
          {
            "abilityText": [
              {
                "type": "plainText",
                "value": "Gain 1 Pain token to immediately move up to 9 spaces to remain adjacent"
              }
            ]
          }
        ]
      }
    ],
    "charges": "2",
    "trireme": "FALSE"
  },
  {
    "cardIDs": [
      "EA2756"
    ],
    "name": "Painkiller Shot",
    "renderType": "Technology",
    "cardType": "Argo Ability",
    "game": "Odyssey",
    "cycle": "Cycle V",
    "cardSize": "Standard",
    "faq": "",
    "errata": "",
    "techType": "Combat",
    "techSubType": "Argo Ability",
    "locked": "FALSE",
    "flavorProject": "A remote Junction command that immediately shuts off the nerves of a Titan",
    "requirements": [
      "Atlantean Armor"
    ],
    "leadsTo": [
      "Meduketos Autopsy"
    ],
    "flavorTech": "A new philosophical protocol allows us to \"trick\" a Titan's nervous system",
    "abilities": [
      {
        "effects": [
          {
            "abilityText": [
              {
                "type": "plainText",
                "value": "Choose a Titan"
              }
            ]
          },
          {
            "abilityText": [
              {
                "type": "plainText",
                "value": "Either lower Pain and/or Bleed gain to 1, or ignore all Pain tokens this Round"
              }
            ]
          }
        ]
      }
    ],
    "charges": "2",
    "trireme": "FALSE"
  },
  {
    "cardIDs": [
      "EA2757"
    ],
    "name": "Triskelion Override",
    "renderType": "Technology",
    "cardType": "Argo Ability",
    "game": "Odyssey",
    "cycle": "Cycle V",
    "cardSize": "Standard",
    "faq": "",
    "errata": "",
    "techType": "Combat",
    "techSubType": "Argo Ability",
    "locked": "FALSE",
    "flavorProject": "A jolt sent through the Junction will override any natural instinct",
    "requirements": [
      "Flash Backstep"
    ],
    "leadsTo": [
      "Silvered Armor"
    ],
    "flavorTech": "Is pushing them this far worth it?",
    "abilities": [
      {
        "effects": [
          {
            "abilityText": [
              {
                "type": "plainText",
                "value": "Choose a Titan"
              }
            ]
          },
          {
            "abilityText": [
              {
                "type": "plainText",
                "value": "Gain 3 Pain tokens to perform a"
              },
              {
                "type": "icon",
                "value": "CombatAction"
              },
              {
                "type": "plainText",
                "value": "or"
              },
              {
                "type": "icon",
                "value": "MovementAction"
              },
              {
                "type": "plainText",
                "value": ", then gain a"
              },
              {
                "type": "icon",
                "value": "CombatAction"
              },
              {
                "type": "plainText",
                "value": "or"
              },
              {
                "type": "icon",
                "value": "MovementAction"
              },
              {
                "type": "plainText",
                "value": "Fatigue token"
              }
            ]
          }
        ]
      }
    ],
    "charges": "2",
    "trireme": "FALSE"
  },
  {
    "cardIDs": [
      "EA2758"
    ],
    "name": "Inner Light",
    "renderType": "Technology",
    "cardType": "Argo Ability",
    "game": "Odyssey",
    "cycle": "Cycle V",
    "cardSize": "Standard",
    "faq": "",
    "errata": "",
    "techType": "Combat",
    "techSubType": "Argo Ability",
    "locked": "FALSE",
    "flavorProject": "A solution of liquid orichalcum introduced into the bloodstream, to be triggered remotely",
    "requirements": [
      "Atlantean Armor"
    ],
    "leadsTo": [
      "Anchor Drop Pod"
    ],
    "flavorTech": "Let there be light",
    "abilities": [
      {
        "effects": [
          {
            "abilityText": [
              {
                "type": "plainText",
                "value": "Choose a Titan that is about to die from"
              },
              {
                "type": "cardRef",
                "value": "Disemboweled",
                "refID": "AM0341"
              },
              {
                "type": "plainText",
                "value": ","
              },
              {
                "type": "cardRef",
                "value": "Fear",
                "refID": "AL0299"
              },
              {
                "type": "plainText",
                "value": ","
              },
              {
                "type": "cardRef",
                "value": "Dread",
                "refID": "AL0299"
              },
              {
                "type": "plainText",
                "value": ","
              },
              {
                "type": "cardRef",
                "value": "Terror",
                "refID": "EL2596"
              },
              {
                "type": "plainText",
                "value": ", or"
              },
              {
                "type": "cardRef",
                "value": "Holy Terror",
                "refID": "EL2596"
              }
            ]
          },
          {
            "abilityText": [
              {
                "type": "plainText",
                "value": "That Titan draws a Grave Trauma instead"
              }
            ]
          }
        ]
      }
    ],
    "charges": "2",
    "trireme": "FALSE"
  },
  {
    "cardIDs": [
      "EA2759"
    ],
    "name": "Anchor Drop Pod",
    "renderType": "Technology",
    "cardType": "Argo Ability",
    "game": "Odyssey",
    "cycle": "Cycle V",
    "cardSize": "Standard",
    "faq": "",
    "errata": "",
    "techType": "Combat",
    "techSubType": "Argo Ability",
    "locked": "FALSE",
    "flavorProject": "Special pods of reinforced materials designed for rapid submersion",
    "requirements": [
      "Inner Light",
      "Meduketos Autopsy"
    ],
    "leadsTo": [
      "Meduketos Live Study"
    ],
    "flavorTech": "Prepare for Titan drop!",
    "abilities": [
      {
        "effects": [
          {
            "abilityText": [
              {
                "type": "plainText",
                "value": "If, during the first Primordial or Titan Round, a Titan dies, replace them with a new Titan from the Stoa"
              }
            ]
          },
          {
            "abilityText": [
              {
                "type": "plainText",
                "value": "Choose a Battle Board space you want to Deploy (see Cycle V, p"
              }
            ]
          },
          {
            "abilityText": [
              {
                "type": "plainText",
                "value": "11) the new Titan to and roll a d10:"
              },
              {
                "type": "newline"
              },
              {
                "type": "plainText",
                "value": "1-5: It lands 3 spaces away from the chosen space in a random direction"
              }
            ]
          },
          {
            "abilityText": [
              {
                "type": "newline"
              },
              {
                "type": "plainText",
                "value": "6-10: It lands on the chosen space"
              }
            ]
          },
          {
            "abilityText": [
              {
                "type": "newline"
              },
              {
                "type": "plainText",
                "value": "If it lands on the Primordial, place 2 Closing and 1 Hope tokens in the Kratos Pool and Deploy the Titan on any adjacent space"
              }
            ]
          }
        ]
      }
    ],
    "charges": "1",
    "trireme": "FALSE"
  },
  {
    "cardIDs": [
      "EA2760"
    ],
    "name": "Soulbalm",
    "renderType": "Technology",
    "cardType": "Argo Ability",
    "game": "Odyssey",
    "cycle": "Cycle V",
    "cardSize": "Standard",
    "faq": "",
    "errata": "",
    "techType": "Combat",
    "techSubType": "Argo Ability",
    "locked": "FALSE",
    "flavorProject": "As we learn to create more nuanced Junction commands, we can speak to the Titan more directly",
    "requirements": [
      "Atlantean Support"
    ],
    "leadsTo": [
      "Dragon of Phobos Live Study"
    ],
    "flavorTech": "Can you hear me? You are not alone in this",
    "abilities": [
      {
        "effects": [
          {
            "abilityText": [
              {
                "type": "plainText",
                "value": "Choose a Titan"
              }
            ]
          },
          {
            "abilityText": [
              {
                "type": "plainText",
                "value": "That Titan discards all Despair tokens or a"
              },
              {
                "type": "cardRef",
                "value": "Fear",
                "refID": "AL0299"
              },
              {
                "type": "plainText",
                "value": "or"
              },
              {
                "type": "cardRef",
                "value": "Terror",
                "refID": "EL2596"
              },
              {
                "type": "plainText",
                "value": "Condition card"
              }
            ]
          }
        ]
      }
    ],
    "charges": "1",
    "trireme": "FALSE"
  }
]